<?xml version="1.0" encoding="UTF-8"?>
<objects serializationModel="Studio.01.07.00">
    <object class="AudioFile" id="{bc2bfacb-a923-4e70-887a-407fbb975a08}">
        <property name="frequencyInKHz">
            <value>44.0999985</value>
        </property>
        <property name="channelCount">
            <value>2</value>
        </property>
        <property name="length">
            <value>6.5</value>
        </property>
        <property name="audioFilePath">
            <value>$(AUDIO_BIN_DIR)/Shrimp cocktail {3c8accd1-bbb4-40f8-9763-8f01a0651dd5}.wav</value>
        </property>
        <relationship name="container">
            <destination>{ab77705a-3170-4fb5-8e8c-65de85c6dcb6}</destination>
        </relationship>
    </object>
</objects>
